CHANGES.txt
LICENSE.txt
MANIFEST.in
README.txt
setup.py
js/__init__.py
js.jquery_formwizard.egg-info/PKG-INFO
js.jquery_formwizard.egg-info/SOURCES.txt
js.jquery_formwizard.egg-info/dependency_links.txt
js.jquery_formwizard.egg-info/entry_points.txt
js.jquery_formwizard.egg-info/namespace_packages.txt
js.jquery_formwizard.egg-info/not-zip-safe
js.jquery_formwizard.egg-info/requires.txt
js.jquery_formwizard.egg-info/top_level.txt
js/jquery_formwizard/__init__.py
js/jquery_formwizard/test_jquery-formwizard.txt
js/jquery_formwizard/resources/.DS_Store
js/jquery_formwizard/resources/jquery.form.wizard.js
js/jquery_formwizard/resources/jquery.form.wizard.min.js