Metadata-Version: 1.0
Name: js.jquery-formwizard
Version: 3.0.5
Summary: Fanstatic packaging of FormWizard for jQuery (jquery.form.wizard.js)
Home-page: https://bitbucket.org/s_nikolai/js.jquery_formwizard
Author: Nikolai Sevostjanov
Author-email: nikolai.sevostjanov@gmail.com
License: BSD
Platform: UNKNOWN
